certbot_dns_hetzner/__init__.py
certbot_dns_hetzner/dns_hetzner.py
certbot_dns_hetzner/dns_hetzner_test.py
certbot_dns_hetzner/fakes.py
certbot_dns_hetzner-3.0.0.dist-info/licenses/LICENSE.txt
certbot_dns_hetzner-3.0.0.dist-info/METADATA
certbot_dns_hetzner-3.0.0.dist-info/WHEEL
certbot_dns_hetzner-3.0.0.dist-info/entry_points.txt
certbot_dns_hetzner-3.0.0.dist-info/top_level.txt
certbot_dns_hetzner-3.0.0.dist-info/RECORD
