Metadata-Version: 2.4
Name: certbot-dns-hetzner
Version: 3.0.0
Summary: This certbot plugin for dns-01 challenge for Hetzner.
Author-email: "control.alt.coop eG" <kontakt@control.alt.coop>
Maintainer-email: "control.alt.coop eG" <kontakt@control.alt.coop>
License-Expression: Apache-2.0
Project-URL: Github, https://github.com/ctrlaltcoop/certbot-dns-hetzner
Classifier: Development Status :: 5 - Production/Stable
Classifier: Environment :: Plugins
Classifier: Intended Audience :: System Administrators
Classifier: Operating System :: POSIX :: Linux
Classifier: Programming Language :: Python
Classifier: Programming Language :: Python :: 3
Classifier: Programming Language :: Python :: 3.10
Classifier: Programming Language :: Python :: 3.11
Classifier: Programming Language :: Python :: 3.12
Classifier: Programming Language :: Python :: 3.13
Classifier: Programming Language :: Python :: 3.14
Classifier: Topic :: Internet :: WWW/HTTP
Classifier: Topic :: Security
Classifier: Topic :: System :: Installation/Setup
Classifier: Topic :: System :: Networking
Classifier: Topic :: System :: Systems Administration
Classifier: Topic :: Utilities
Requires-Python: >=3.10
License-File: LICENSE.txt
Requires-Dist: certbot>=2.0.0
Requires-Dist: dns-lexicon-coop>=3.24.2
Requires-Dist: parsedatetime>=2.6
Requires-Dist: requests>=2.32.5
Requires-Dist: requests-mock>=1.12.1
Requires-Dist: setuptools>=80.9.0
Dynamic: license-file
